example/__init__.py
example/direct_policy_search_for_gym/__init__.py
example/direct_policy_search_for_gym/gym_task.py
example/direct_policy_search_for_gym/nn_model.py
example/direct_policy_search_for_gym/run.py
example/linear_classifier_using_ramploss/__init__.py
example/linear_classifier_using_ramploss/ramploss.py
example/sequential_random_embedding/__init__.py
example/sequential_random_embedding/continuous_sre_opt.py
example/sequential_random_embedding/sphere_sre.py
example/simple_functions/__init__.py
example/simple_functions/continuous_opt.py
example/simple_functions/discrete_opt.py
example/simple_functions/discrete_with_order_opt.py
example/simple_functions/function_test1.py
example/simple_functions/mixed_opt.py
example/simple_functions/opt_under_noise.py
example/simple_functions/opt_with_stopping_criterion.py
example/simple_functions/quick_start.py
example/simple_functions/simple_function.py
example/sparse_regression/__init__.py
example/sparse_regression/ponss_opt.py
example/sparse_regression/poss_opt.py
example/sparse_regression/sparse_mse.py
zoopt/__init__.py
zoopt/dimension.py
zoopt/exp_opt.py
zoopt/objective.py
zoopt/opt.py
zoopt/parameter.py
zoopt/solution.py
zoopt/algos/__init__.py
zoopt/algos/high_dimensionality_handling/__init__.py
zoopt/algos/high_dimensionality_handling/sre_optimization.py
zoopt/algos/noise_handling/__init__.py
zoopt/algos/noise_handling/ponss.py
zoopt/algos/noise_handling/ssracos.py
zoopt/algos/opt_algorithms/__init__.py
zoopt/algos/opt_algorithms/paretoopt/__init__.py
zoopt/algos/opt_algorithms/paretoopt/pareto_optimization.py
zoopt/algos/opt_algorithms/paretoopt/paretoopt.py
zoopt/algos/opt_algorithms/racos/__init__.py
zoopt/algos/opt_algorithms/racos/asracos.py
zoopt/algos/opt_algorithms/racos/racos.py
zoopt/algos/opt_algorithms/racos/racos_classification.py
zoopt/algos/opt_algorithms/racos/racos_common.py
zoopt/algos/opt_algorithms/racos/racos_optimization.py
zoopt/algos/opt_algorithms/racos/sracos.py
zoopt/utils/__init__.py
zoopt-0.4.2.dist-info/LICENSE.txt
zoopt-0.4.2.dist-info/METADATA
zoopt-0.4.2.dist-info/WHEEL
zoopt-0.4.2.dist-info/top_level.txt
zoopt-0.4.2.dist-info/RECORD
