Metadata-Version: 2.1
Name: zoopt
Version: 0.4.2
Summary: A Python Package for Zeroth-Order Optimization
Home-page: https://github.com/polixir/ZOOpt
Author: Yang Yu
Author-email: yuy@nju.edu.cn
Maintainer: Yu-Ren Liu, Xiong-Hui Chen, Yi-Qi Hu, Chao Feng, Yang Yu
License: MIT License
Platform: all
Classifier: Development Status :: 4 - Beta
Classifier: Operating System :: OS Independent
Classifier: Intended Audience :: Developers
Classifier: License :: OSI Approved :: MIT License
Classifier: Programming Language :: Python
Classifier: Programming Language :: Python :: Implementation
Classifier: Programming Language :: Python :: 3
Classifier: Programming Language :: Python :: 3.5
Classifier: Programming Language :: Python :: 3.6
Classifier: Programming Language :: Python :: 3.7
Classifier: Programming Language :: Python :: 3.8
Classifier: Topic :: Software Development :: Libraries
License-File: LICENSE.txt
Requires-Dist: numpy
Requires-Dist: matplotlib
